obs_img_utils/__init__.py
obs_img_utils/api.py
obs_img_utils/cli.py
obs_img_utils/exceptions.py
obs_img_utils/rpm.py
obs_img_utils/utils.py
obs_img_utils/web_content.py
obs_img_utils-1.11.0.dist-info/licenses/LICENSE
obs_img_utils-1.11.0.dist-info/METADATA
obs_img_utils-1.11.0.dist-info/WHEEL
obs_img_utils-1.11.0.dist-info/entry_points.txt
obs_img_utils-1.11.0.dist-info/top_level.txt
obs_img_utils-1.11.0.dist-info/RECORD
